guacli/__init__.py
guacli/cli.py
guacli/guacamoleClient.py
guacli-1.1.3.dist-info/licenses/LICENSE
guacli-1.1.3.dist-info/METADATA
guacli-1.1.3.dist-info/WHEEL
guacli-1.1.3.dist-info/entry_points.txt
guacli-1.1.3.dist-info/top_level.txt
guacli-1.1.3.dist-info/RECORD
