Metadata-Version: 2.4
Name: guacli
Version: 1.1.3
Summary: Python client (library and CLI) for Apache Guacamole front-end REST API.
Home-page: https://github.com/chaimeleon-eu/guacamole-python-client
Author: Pau Lozano
Author-email: 
License: Apache 2.0
Keywords: cli client guacamole api
License-File: LICENSE
Dynamic: author
Dynamic: description
Dynamic: description-content-type
Dynamic: home-page
Dynamic: keywords
Dynamic: license
Dynamic: license-file
Dynamic: summary
